appsec_discovery/__init__.py
appsec_discovery/cli.py
appsec_discovery/models/__init__.py
appsec_discovery/models/code_object.py
appsec_discovery/models/config.py
appsec_discovery/models/reports.py
appsec_discovery/models/uploads.py
appsec_discovery/parsers/__init__.py
appsec_discovery/parsers/base_parser.py
appsec_discovery/parsers/client/parser.py
appsec_discovery/parsers/db/parser.py
appsec_discovery/parsers/golang/parser.py
appsec_discovery/parsers/golang/scanner_rules/dto.yaml
appsec_discovery/parsers/graphql/parser.py
appsec_discovery/parsers/java/parser.py
appsec_discovery/parsers/java/scanner_rules/dto.yaml
appsec_discovery/parsers/javascript/parser.py
appsec_discovery/parsers/javascript/scanner_rules/query.yaml
appsec_discovery/parsers/parser_factory.py
appsec_discovery/parsers/protobuf/parser.py
appsec_discovery/parsers/python/parser.py
appsec_discovery/parsers/python/scanner_rules/dto.yaml
appsec_discovery/parsers/python/scanner_rules/route.yaml
appsec_discovery/parsers/swagger/parser.py
appsec_discovery/parsers/terraform/parser.py
appsec_discovery/parsers/terraform/scanner_rules/rules.yaml
appsec_discovery/services/__init__.py
appsec_discovery/services/ai_service.py
appsec_discovery/services/report_service.py
appsec_discovery/services/scan_service.py
appsec_discovery/services/upload_service.py
appsec_discovery-0.8.3.dist-info/LICENSE
appsec_discovery-0.8.3.dist-info/METADATA
appsec_discovery-0.8.3.dist-info/WHEEL
appsec_discovery-0.8.3.dist-info/entry_points.txt
appsec_discovery-0.8.3.dist-info/RECORD
