Metadata-Version: 2.3
Name: appsec-discovery
Version: 0.8.3
Summary: Discover sensitive objects in project code
License: MIT
Keywords: security,assets,discovery,scanning,appsec
Author: Dmitrii Mariushkin
Author-email: d.v.marushkin@gmail.com
Requires-Python: >=3.12,<4.0
Classifier: Environment :: Console
Classifier: License :: OSI Approved :: MIT License
Classifier: Operating System :: OS Independent
Classifier: Programming Language :: Python :: 3
Classifier: Programming Language :: Python :: 3.12
Classifier: Programming Language :: Python :: 3.13
Classifier: Topic :: Security
Requires-Dist: click (>=8.1.7,<9.0.0)
Requires-Dist: click-loglevel (>=0.5.0,<0.6.0)
Requires-Dist: graphql-core (>=3.2.5,<4.0.0)
Requires-Dist: huggingface-hub (>=0.26.2,<0.27.0)
Requires-Dist: jschema-to-python (>=1.2.3,<2.0.0)
Requires-Dist: llama-cpp-python (>=0.3.1,<0.4.0)
Requires-Dist: mkdocs-material (>=9.5.44,<10.0.0)
Requires-Dist: openai (>=1.60.1,<2.0.0)
Requires-Dist: openapi3-parser (>=1.1.19,<2.0.0)
Requires-Dist: proto-schema-parser (>=1.4.2,<2.0.0)
Requires-Dist: pydantic (==1.10.13)
Requires-Dist: pyyaml (>=6.0.2,<7.0.0)
Requires-Dist: sarif-om (>=1.0.4,<2.0.0)
Requires-Dist: semgrep (==1.62)
Project-URL: Bug Tracker, https://github.com/dmarushkin/appsec-discovery/issues
Project-URL: Homepage, https://github.com/dmarushkin/appsec-discovery
